<?xml version="1.0" encoding="UTF-8"?><record_update table="sn_ex_sp_task_tab_configuration">
    <sn_ex_sp_task_tab_configuration action="DELETE">
        <active>true</active>
        <child_table/>
        <fields/>
        <name>Attachments</name>
        <order>200</order>
        <script>false</script>
        <source>approval</source>
        <sys_class_name>sn_ex_sp_task_tab_configuration</sys_class_name>
        <sys_created_by>admin</sys_created_by>
        <sys_created_on>2023-04-10 12:50:00</sys_created_on>
        <sys_id>a8d550ba474e2190901d3a34846d43ad</sys_id>
        <sys_mod_count>1</sys_mod_count>
        <sys_name>Attachments</sys_name>
        <sys_package display_value="HR Service Delivery Integration with Workday" source="sn_hr_workday">d4fb8bd8db5b0010205cdf6b5e96190e</sys_package>
        <sys_policy/>
        <sys_scope display_value="HR Service Delivery Integration with Workday">d4fb8bd8db5b0010205cdf6b5e96190e</sys_scope>
        <sys_update_name>sn_ex_sp_task_tab_configuration_a8d550ba474e2190901d3a34846d43ad</sys_update_name>
        <sys_updated_by>admin</sys_updated_by>
        <sys_updated_on>2023-04-10 12:51:39</sys_updated_on>
        <table>sys_user</table>
        <task_configuration display_value="Approval l Workday | Time off request">ae84d43a474e2190901d3a34846d43d5</task_configuration>
        <type>attachments</type>
        <visibility/>
        <visibility_script><![CDATA[/**
 * `answer` should be returned with true/false which validates if a tab is visible
 * The `current` object refers to the current Task(extension) record 
 **/ 
(function(current, answer) { 

	// write your code here 

	answer = true; 
	return answer; 
 
})(current, answer);]]></visibility_script>
        <widget/>
        <widget_parameters/>
    </sn_ex_sp_task_tab_configuration>
    <sys_update_version action="INSERT_OR_UPDATE">
        <action>DELETE</action>
        <application display_value="HR Service Delivery Integration with Workday">d4fb8bd8db5b0010205cdf6b5e96190e</application>
        <file_path/>
        <instance_id>b5713642dbe621d868c2c59705961942</instance_id>
        <instance_name>wdappdev2</instance_name>
        <name>sn_ex_sp_task_tab_configuration_a8d550ba474e2190901d3a34846d43ad</name>
        <payload>&lt;?xml version="1.0" encoding="UTF-8"?&gt;&lt;record_update table="sn_ex_sp_task_tab_configuration"&gt;&lt;sn_ex_sp_task_tab_configuration action="INSERT_OR_UPDATE"&gt;&lt;active&gt;true&lt;/active&gt;&lt;child_table/&gt;&lt;fields/&gt;&lt;name&gt;Attachments&lt;/name&gt;&lt;order&gt;200&lt;/order&gt;&lt;script&gt;false&lt;/script&gt;&lt;source&gt;approval&lt;/source&gt;&lt;sys_class_name&gt;sn_ex_sp_task_tab_configuration&lt;/sys_class_name&gt;&lt;sys_created_by&gt;admin&lt;/sys_created_by&gt;&lt;sys_created_on&gt;2023-04-10 12:50:00&lt;/sys_created_on&gt;&lt;sys_id&gt;a8d550ba474e2190901d3a34846d43ad&lt;/sys_id&gt;&lt;sys_mod_count&gt;1&lt;/sys_mod_count&gt;&lt;sys_name&gt;Attachments&lt;/sys_name&gt;&lt;sys_package display_value="HR Service Delivery Integration with Workday" source="sn_hr_workday"&gt;d4fb8bd8db5b0010205cdf6b5e96190e&lt;/sys_package&gt;&lt;sys_policy/&gt;&lt;sys_scope display_value="HR Service Delivery Integration with Workday"&gt;d4fb8bd8db5b0010205cdf6b5e96190e&lt;/sys_scope&gt;&lt;sys_update_name&gt;sn_ex_sp_task_tab_configuration_a8d550ba474e2190901d3a34846d43ad&lt;/sys_update_name&gt;&lt;sys_updated_by&gt;admin&lt;/sys_updated_by&gt;&lt;sys_updated_on&gt;2023-04-10 12:51:39&lt;/sys_updated_on&gt;&lt;table&gt;sys_user&lt;/table&gt;&lt;task_configuration display_value="Approval l Workday | Time off request"&gt;ae84d43a474e2190901d3a34846d43d5&lt;/task_configuration&gt;&lt;type&gt;attachments&lt;/type&gt;&lt;visibility/&gt;&lt;visibility_script&gt;&lt;![CDATA[/**
 * `answer` should be returned with true/false which validates if a tab is visible
 * The `current` object refers to the current Task(extension) record 
 **/ 
(function(current, answer) { 

	// write your code here 

	answer = true; 
	return answer; 
 
})(current, answer);]]&gt;&lt;/visibility_script&gt;&lt;widget/&gt;&lt;widget_parameters/&gt;&lt;/sn_ex_sp_task_tab_configuration&gt;&lt;/record_update&gt;</payload>
        <payload_hash>-1166216546</payload_hash>
        <record_name>Attachments</record_name>
        <reverted_from/>
        <source>80bae28c4772611072cf2ebd416d435c</source>
        <source_table>sys_update_set</source_table>
        <state>previous</state>
        <sys_created_by>admin</sys_created_by>
        <sys_created_on>2023-05-09 17:25:55</sys_created_on>
        <sys_id>5b2be60047b2611072cf2ebd416d4371</sys_id>
        <sys_mod_count>0</sys_mod_count>
        <sys_recorded_at>188018c5c6b0000001</sys_recorded_at>
        <sys_updated_by>admin</sys_updated_by>
        <sys_updated_on>2023-05-09 17:25:55</sys_updated_on>
        <type>Tab Configuration</type>
        <update_guid>c74698bac44e2190e69920f98cd3f410</update_guid>
        <update_guid_history>c74698bac44e2190e69920f98cd3f410:-1166216546,f6e590ba384e21902b8e49670f53fbd4:-924379107</update_guid_history>
    </sys_update_version>
    <sys_metadata_delete action="INSERT_OR_UPDATE">
        <sys_audit_delete display_value="Attachments">c71c62c047b2611072cf2ebd416d43ca</sys_audit_delete>
        <sys_class_name>sys_metadata_delete</sys_class_name>
        <sys_created_by>admin</sys_created_by>
        <sys_created_on>2023-05-09 17:30:00</sys_created_on>
        <sys_db_object display_value="" name="sn_ex_sp_task_tab_configuration">sn_ex_sp_task_tab_configuration</sys_db_object>
        <sys_id>18f2aceda5064cc984393a136bad01a1</sys_id>
        <sys_metadata>a8d550ba474e2190901d3a34846d43ad</sys_metadata>
        <sys_mod_count>0</sys_mod_count>
        <sys_name>Attachments</sys_name>
        <sys_package display_value="HR Service Delivery Integration with Workday" source="sn_hr_workday">d4fb8bd8db5b0010205cdf6b5e96190e</sys_package>
        <sys_parent/>
        <sys_policy/>
        <sys_scope display_value="HR Service Delivery Integration with Workday">d4fb8bd8db5b0010205cdf6b5e96190e</sys_scope>
        <sys_scope_delete display_value="">2b72f0f872474230a9dbcdf31f5e5440</sys_scope_delete>
        <sys_update_name>sn_ex_sp_task_tab_configuration_a8d550ba474e2190901d3a34846d43ad</sys_update_name>
        <sys_update_version display_value="sn_ex_sp_task_tab_configuration_a8d550ba474e2190901d3a34846d43ad">5b2be60047b2611072cf2ebd416d4371</sys_update_version>
        <sys_updated_by>admin</sys_updated_by>
        <sys_updated_on>2023-05-09 17:30:00</sys_updated_on>
    </sys_metadata_delete>
</record_update>
