<?xml version="1.0" encoding="UTF-8"?><record_update>
    <sys_ui_section action="DELETE" caption="" section_id="7b5d877b47456510901d3a34846d4326" sys_domain="global" table="sn_hr_workday_time_off_requests" version="3" view="">
        <sys_ui_element action="INSERT_OR_UPDATE">
            <element>.begin_split</element>
            <position>0</position>
            <sys_created_by>admin</sys_created_by>
            <sys_created_on>2023-02-23 11:42:40</sys_created_on>
            <sys_id>7b5d877b47456510901d3a34846d4352</sys_id>
            <sys_mod_count>0</sys_mod_count>
            <sys_ui_formatter/>
            <sys_ui_section caption="NULL" display_value="" name="sn_hr_workday_time_off_requests" sys_domain="global" view="Default view">7b5d877b47456510901d3a34846d4326</sys_ui_section>
            <sys_updated_by>admin</sys_updated_by>
            <sys_updated_on>2023-02-23 11:42:40</sys_updated_on>
            <sys_user/>
            <type>.begin_split</type>
        </sys_ui_element>
        <sys_ui_element action="INSERT_OR_UPDATE">
            <element>u_type_of_leave</element>
            <position>1</position>
            <sys_created_by>admin</sys_created_by>
            <sys_created_on>2023-02-23 11:42:40</sys_created_on>
            <sys_id>fb5d877b47456510901d3a34846d4352</sys_id>
            <sys_mod_count>0</sys_mod_count>
            <sys_ui_formatter/>
            <sys_ui_section caption="NULL" display_value="" name="sn_hr_workday_time_off_requests" sys_domain="global" view="Default view">7b5d877b47456510901d3a34846d4326</sys_ui_section>
            <sys_updated_by>admin</sys_updated_by>
            <sys_updated_on>2023-02-23 11:42:40</sys_updated_on>
            <sys_user/>
            <type/>
        </sys_ui_element>
        <sys_ui_element action="INSERT_OR_UPDATE">
            <element>u_total_requested_with_units</element>
            <position>2</position>
            <sys_created_by>admin</sys_created_by>
            <sys_created_on>2023-02-23 11:42:40</sys_created_on>
            <sys_id>7f5d877b47456510901d3a34846d4352</sys_id>
            <sys_mod_count>0</sys_mod_count>
            <sys_ui_formatter/>
            <sys_ui_section caption="NULL" display_value="" name="sn_hr_workday_time_off_requests" sys_domain="global" view="Default view">7b5d877b47456510901d3a34846d4326</sys_ui_section>
            <sys_updated_by>admin</sys_updated_by>
            <sys_updated_on>2023-02-23 11:42:40</sys_updated_on>
            <sys_user/>
            <type/>
        </sys_ui_element>
        <sys_ui_element action="INSERT_OR_UPDATE">
            <element>u_first_day_of_time_off</element>
            <position>3</position>
            <sys_created_by>admin</sys_created_by>
            <sys_created_on>2023-02-23 11:42:40</sys_created_on>
            <sys_id>ff5d877b47456510901d3a34846d4352</sys_id>
            <sys_mod_count>0</sys_mod_count>
            <sys_ui_formatter/>
            <sys_ui_section caption="NULL" display_value="" name="sn_hr_workday_time_off_requests" sys_domain="global" view="Default view">7b5d877b47456510901d3a34846d4326</sys_ui_section>
            <sys_updated_by>admin</sys_updated_by>
            <sys_updated_on>2023-02-23 11:42:40</sys_updated_on>
            <sys_user/>
            <type/>
        </sys_ui_element>
        <sys_ui_element action="INSERT_OR_UPDATE">
            <element>.split</element>
            <position>4</position>
            <sys_created_by>admin</sys_created_by>
            <sys_created_on>2023-02-23 11:42:40</sys_created_on>
            <sys_id>735d877b47456510901d3a34846d4353</sys_id>
            <sys_mod_count>0</sys_mod_count>
            <sys_ui_formatter/>
            <sys_ui_section caption="NULL" display_value="" name="sn_hr_workday_time_off_requests" sys_domain="global" view="Default view">7b5d877b47456510901d3a34846d4326</sys_ui_section>
            <sys_updated_by>admin</sys_updated_by>
            <sys_updated_on>2023-02-23 11:42:40</sys_updated_on>
            <sys_user/>
            <type>.split</type>
        </sys_ui_element>
        <sys_ui_element action="INSERT_OR_UPDATE">
            <element>u_attachments</element>
            <position>5</position>
            <sys_created_by>admin</sys_created_by>
            <sys_created_on>2023-02-23 11:42:40</sys_created_on>
            <sys_id>f35d877b47456510901d3a34846d4353</sys_id>
            <sys_mod_count>0</sys_mod_count>
            <sys_ui_formatter/>
            <sys_ui_section caption="NULL" display_value="" name="sn_hr_workday_time_off_requests" sys_domain="global" view="Default view">7b5d877b47456510901d3a34846d4326</sys_ui_section>
            <sys_updated_by>admin</sys_updated_by>
            <sys_updated_on>2023-02-23 11:42:40</sys_updated_on>
            <sys_user/>
            <type/>
        </sys_ui_element>
        <sys_ui_element action="INSERT_OR_UPDATE">
            <element>u_last_day_of_time_off</element>
            <position>6</position>
            <sys_created_by>admin</sys_created_by>
            <sys_created_on>2023-02-23 11:42:40</sys_created_on>
            <sys_id>775d877b47456510901d3a34846d4353</sys_id>
            <sys_mod_count>0</sys_mod_count>
            <sys_ui_formatter/>
            <sys_ui_section caption="NULL" display_value="" name="sn_hr_workday_time_off_requests" sys_domain="global" view="Default view">7b5d877b47456510901d3a34846d4326</sys_ui_section>
            <sys_updated_by>admin</sys_updated_by>
            <sys_updated_on>2023-02-23 11:42:40</sys_updated_on>
            <sys_user/>
            <type/>
        </sys_ui_element>
        <sys_ui_element action="INSERT_OR_UPDATE">
            <element>u_comments</element>
            <position>7</position>
            <sys_created_by>admin</sys_created_by>
            <sys_created_on>2023-02-23 11:42:40</sys_created_on>
            <sys_id>f75d877b47456510901d3a34846d4353</sys_id>
            <sys_mod_count>0</sys_mod_count>
            <sys_ui_formatter/>
            <sys_ui_section caption="NULL" display_value="" name="sn_hr_workday_time_off_requests" sys_domain="global" view="Default view">7b5d877b47456510901d3a34846d4326</sys_ui_section>
            <sys_updated_by>admin</sys_updated_by>
            <sys_updated_on>2023-02-23 11:42:40</sys_updated_on>
            <sys_user/>
            <type/>
        </sys_ui_element>
        <sys_ui_element action="INSERT_OR_UPDATE">
            <element>.end_split</element>
            <position>8</position>
            <sys_created_by>admin</sys_created_by>
            <sys_created_on>2023-02-23 11:42:40</sys_created_on>
            <sys_id>7b5d877b47456510901d3a34846d4353</sys_id>
            <sys_mod_count>0</sys_mod_count>
            <sys_ui_formatter/>
            <sys_ui_section caption="NULL" display_value="" name="sn_hr_workday_time_off_requests" sys_domain="global" view="Default view">7b5d877b47456510901d3a34846d4326</sys_ui_section>
            <sys_updated_by>admin</sys_updated_by>
            <sys_updated_on>2023-02-23 11:42:40</sys_updated_on>
            <sys_user/>
            <type>.end_split</type>
        </sys_ui_element>
        <sys_ui_element action="INSERT_OR_UPDATE">
            <element>u_action_event</element>
            <position>9</position>
            <sys_created_by>admin</sys_created_by>
            <sys_created_on>2023-02-24 08:49:26</sys_created_on>
            <sys_id>c05f63848751a51018c742ec0ebb356d</sys_id>
            <sys_mod_count>0</sys_mod_count>
            <sys_ui_formatter/>
            <sys_ui_section caption="NULL" display_value="" name="sn_hr_workday_time_off_requests" sys_domain="global" view="Default view">7b5d877b47456510901d3a34846d4326</sys_ui_section>
            <sys_updated_by>admin</sys_updated_by>
            <sys_updated_on>2023-02-24 08:49:26</sys_updated_on>
            <sys_user/>
            <type/>
        </sys_ui_element>
        <sys_ui_element action="INSERT_OR_UPDATE">
            <element>u_workday_todos</element>
            <position>10</position>
            <sys_created_by>admin</sys_created_by>
            <sys_created_on>2023-02-24 11:29:19</sys_created_on>
            <sys_id>b5e3581c4755a510901d3a34846d43f8</sys_id>
            <sys_mod_count>0</sys_mod_count>
            <sys_ui_formatter/>
            <sys_ui_section caption="NULL" display_value="" name="sn_hr_workday_time_off_requests" sys_domain="global" view="Default view">7b5d877b47456510901d3a34846d4326</sys_ui_section>
            <sys_updated_by>admin</sys_updated_by>
            <sys_updated_on>2023-02-24 11:29:19</sys_updated_on>
            <sys_user/>
            <type/>
        </sys_ui_element>
        <sys_ui_element action="INSERT_OR_UPDATE">
            <element>u_workday_id</element>
            <position>11</position>
            <sys_created_by>admin</sys_created_by>
            <sys_created_on>2023-02-27 05:13:25</sys_created_on>
            <sys_id>30aa9e8d47dd2910901d3a34846d4353</sys_id>
            <sys_mod_count>0</sys_mod_count>
            <sys_ui_formatter/>
            <sys_ui_section caption="NULL" display_value="" name="sn_hr_workday_time_off_requests" sys_domain="global" view="Default view">7b5d877b47456510901d3a34846d4326</sys_ui_section>
            <sys_updated_by>admin</sys_updated_by>
            <sys_updated_on>2023-02-27 05:13:25</sys_updated_on>
            <sys_user/>
            <type/>
        </sys_ui_element>
        <sys_ui_element action="INSERT_OR_UPDATE">
            <element>u_workdayid</element>
            <position>12</position>
            <sys_created_by>admin</sys_created_by>
            <sys_created_on>2023-03-02 08:00:10</sys_created_on>
            <sys_id>349d52c2475d2d10901d3a34846d43ca</sys_id>
            <sys_mod_count>0</sys_mod_count>
            <sys_ui_formatter/>
            <sys_ui_section caption="NULL" display_value="" name="sn_hr_workday_time_off_requests" sys_domain="global" view="Default view">7b5d877b47456510901d3a34846d4326</sys_ui_section>
            <sys_updated_by>admin</sys_updated_by>
            <sys_updated_on>2023-03-02 08:00:10</sys_updated_on>
            <sys_user/>
            <type/>
        </sys_ui_element>
        <sys_ui_element action="INSERT_OR_UPDATE">
            <element>u_time_off_total_units_days</element>
            <position>13</position>
            <sys_created_by>admin</sys_created_by>
            <sys_created_on>2023-03-02 08:00:26</sys_created_on>
            <sys_id>38ad92c2475d2d10901d3a34846d438c</sys_id>
            <sys_mod_count>0</sys_mod_count>
            <sys_ui_formatter/>
            <sys_ui_section caption="NULL" display_value="" name="sn_hr_workday_time_off_requests" sys_domain="global" view="Default view">7b5d877b47456510901d3a34846d4326</sys_ui_section>
            <sys_updated_by>admin</sys_updated_by>
            <sys_updated_on>2023-03-02 08:00:26</sys_updated_on>
            <sys_user/>
            <type/>
        </sys_ui_element>
        <sys_ui_element action="INSERT_OR_UPDATE">
            <element>u_time_off_total_units_hours</element>
            <position>14</position>
            <sys_created_by>admin</sys_created_by>
            <sys_created_on>2023-03-02 08:00:34</sys_created_on>
            <sys_id>32add2c2475d2d10901d3a34846d4319</sys_id>
            <sys_mod_count>0</sys_mod_count>
            <sys_ui_formatter/>
            <sys_ui_section caption="NULL" display_value="" name="sn_hr_workday_time_off_requests" sys_domain="global" view="Default view">7b5d877b47456510901d3a34846d4326</sys_ui_section>
            <sys_updated_by>admin</sys_updated_by>
            <sys_updated_on>2023-03-02 08:00:34</sys_updated_on>
            <sys_user/>
            <type/>
        </sys_ui_element>
        <sys_ui_element action="INSERT_OR_UPDATE">
            <element>u_date</element>
            <position>15</position>
            <sys_created_by>admin</sys_created_by>
            <sys_created_on>2023-03-02 08:00:40</sys_created_on>
            <sys_id>08bdd2c2475d2d10901d3a34846d43a5</sys_id>
            <sys_mod_count>0</sys_mod_count>
            <sys_ui_formatter/>
            <sys_ui_section caption="NULL" display_value="" name="sn_hr_workday_time_off_requests" sys_domain="global" view="Default view">7b5d877b47456510901d3a34846d4326</sys_ui_section>
            <sys_updated_by>admin</sys_updated_by>
            <sys_updated_on>2023-03-02 08:00:40</sys_updated_on>
            <sys_user/>
            <type/>
        </sys_ui_element>
        <sys_ui_element action="INSERT_OR_UPDATE">
            <element>u_day_of_the_week</element>
            <position>16</position>
            <sys_created_by>admin</sys_created_by>
            <sys_created_on>2023-03-02 08:00:45</sys_created_on>
            <sys_id>59bdd2c2475d2d10901d3a34846d43e7</sys_id>
            <sys_mod_count>0</sys_mod_count>
            <sys_ui_formatter/>
            <sys_ui_section caption="NULL" display_value="" name="sn_hr_workday_time_off_requests" sys_domain="global" view="Default view">7b5d877b47456510901d3a34846d4326</sys_ui_section>
            <sys_updated_by>admin</sys_updated_by>
            <sys_updated_on>2023-03-02 08:00:45</sys_updated_on>
            <sys_user/>
            <type/>
        </sys_ui_element>
        <sys_ui_element action="INSERT_OR_UPDATE">
            <element>u_time_off_type_for_time_off_entry</element>
            <position>17</position>
            <sys_created_by>admin</sys_created_by>
            <sys_created_on>2023-03-02 08:00:50</sys_created_on>
            <sys_id>6abd16c2475d2d10901d3a34846d4342</sys_id>
            <sys_mod_count>0</sys_mod_count>
            <sys_ui_formatter/>
            <sys_ui_section caption="NULL" display_value="" name="sn_hr_workday_time_off_requests" sys_domain="global" view="Default view">7b5d877b47456510901d3a34846d4326</sys_ui_section>
            <sys_updated_by>admin</sys_updated_by>
            <sys_updated_on>2023-03-02 08:00:50</sys_updated_on>
            <sys_user/>
            <type/>
        </sys_ui_element>
        <sys_ui_element action="INSERT_OR_UPDATE">
            <element>u_units_requested_this_coordinated_leave_time_off</element>
            <position>18</position>
            <sys_created_by>admin</sys_created_by>
            <sys_created_on>2023-03-02 08:00:54</sys_created_on>
            <sys_id>afbd16c2475d2d10901d3a34846d436b</sys_id>
            <sys_mod_count>0</sys_mod_count>
            <sys_ui_formatter/>
            <sys_ui_section caption="NULL" display_value="" name="sn_hr_workday_time_off_requests" sys_domain="global" view="Default view">7b5d877b47456510901d3a34846d4326</sys_ui_section>
            <sys_updated_by>admin</sys_updated_by>
            <sys_updated_on>2023-03-02 08:00:54</sys_updated_on>
            <sys_user/>
            <type/>
        </sys_ui_element>
        <sys_ui_element action="INSERT_OR_UPDATE">
            <element>u_unitoftime</element>
            <position>19</position>
            <sys_created_by>admin</sys_created_by>
            <sys_created_on>2023-03-02 08:00:57</sys_created_on>
            <sys_id>d8cd16c2475d2d10901d3a34846d43a1</sys_id>
            <sys_mod_count>0</sys_mod_count>
            <sys_ui_formatter/>
            <sys_ui_section caption="NULL" display_value="" name="sn_hr_workday_time_off_requests" sys_domain="global" view="Default view">7b5d877b47456510901d3a34846d4326</sys_ui_section>
            <sys_updated_by>admin</sys_updated_by>
            <sys_updated_on>2023-03-02 08:00:57</sys_updated_on>
            <sys_user/>
            <type/>
        </sys_ui_element>
        <sys_ui_element action="INSERT_OR_UPDATE">
            <element>u_taskitemuniqueid</element>
            <position>20</position>
            <sys_created_by>admin</sys_created_by>
            <sys_created_on>2023-03-02 08:40:05</sys_created_on>
            <sys_id>29b6a6ca475d2d10901d3a34846d43c5</sys_id>
            <sys_mod_count>0</sys_mod_count>
            <sys_ui_formatter/>
            <sys_ui_section caption="NULL" display_value="" name="sn_hr_workday_time_off_requests" sys_domain="global" view="Default view">7b5d877b47456510901d3a34846d4326</sys_ui_section>
            <sys_updated_by>admin</sys_updated_by>
            <sys_updated_on>2023-03-02 08:40:05</sys_updated_on>
            <sys_user/>
            <type/>
        </sys_ui_element>
        <sys_ui_element action="INSERT_OR_UPDATE">
            <element>u_time_off_request_parent</element>
            <position>21</position>
            <sys_created_by>admin</sys_created_by>
            <sys_created_on>2023-03-23 05:57:59</sys_created_on>
            <sys_id>bffa02b047312150901d3a34846d4303</sys_id>
            <sys_mod_count>0</sys_mod_count>
            <sys_ui_formatter/>
            <sys_ui_section caption="NULL" display_value="" name="sn_hr_workday_time_off_requests" sys_domain="global" view="Default view">7b5d877b47456510901d3a34846d4326</sys_ui_section>
            <sys_updated_by>admin</sys_updated_by>
            <sys_updated_on>2023-03-23 05:57:59</sys_updated_on>
            <sys_user/>
            <type/>
        </sys_ui_element>
        <sys_ui_element action="INSERT_OR_UPDATE">
            <element>u_use_case_type</element>
            <position>22</position>
            <sys_created_by>admin</sys_created_by>
            <sys_created_on>2023-03-31 05:37:12</sys_created_on>
            <sys_id>91f2df5787fd611018c742ec0ebb358f</sys_id>
            <sys_mod_count>0</sys_mod_count>
            <sys_ui_formatter/>
            <sys_ui_section caption="NULL" display_value="" name="sn_hr_workday_time_off_requests" sys_domain="global" view="Default view">7b5d877b47456510901d3a34846d4326</sys_ui_section>
            <sys_updated_by>admin</sys_updated_by>
            <sys_updated_on>2023-03-31 05:37:12</sys_updated_on>
            <sys_user/>
            <type/>
        </sys_ui_element>
        <sys_ui_section action="DELETE">
            <caption/>
            <header>false</header>
            <name>sn_hr_workday_time_off_requests</name>
            <roles/>
            <sys_class_name>sys_ui_section</sys_class_name>
            <sys_created_by>admin</sys_created_by>
            <sys_created_on>2023-02-23 11:42:40</sys_created_on>
            <sys_domain>global</sys_domain>
            <sys_domain_path>/</sys_domain_path>
            <sys_id>7b5d877b47456510901d3a34846d4326</sys_id>
            <sys_mod_count>0</sys_mod_count>
            <sys_name>sn_hr_workday_time_off_requests</sys_name>
            <sys_overrides/>
            <sys_package display_value="HR Service Delivery Integration with Workday" source="sn_hr_workday">d4fb8bd8db5b0010205cdf6b5e96190e</sys_package>
            <sys_policy/>
            <sys_scope display_value="HR Service Delivery Integration with Workday">d4fb8bd8db5b0010205cdf6b5e96190e</sys_scope>
            <sys_update_name>sys_ui_section_7b5d877b47456510901d3a34846d4326</sys_update_name>
            <sys_updated_by>admin</sys_updated_by>
            <sys_updated_on>2023-02-23 11:42:40</sys_updated_on>
            <sys_user/>
            <title>true</title>
            <view display_value="Default view" name="NULL">Default view</view>
            <view_name/>
        </sys_ui_section>
    </sys_ui_section>
    <sys_update_version action="INSERT_OR_UPDATE">
        <action>DELETE</action>
        <application display_value="HR Service Delivery Integration with Workday">d4fb8bd8db5b0010205cdf6b5e96190e</application>
        <file_path/>
        <instance_id>b5713642dbe621d868c2c59705961942</instance_id>
        <instance_name>wdappdev2</instance_name>
        <name>sys_ui_section_7b5d877b47456510901d3a34846d4326</name>
        <payload><![CDATA[<?xml version="1.0" encoding="UTF-8"?><record_update><sys_ui_section caption="" section_id="7b5d877b47456510901d3a34846d4326" sys_domain="global" table="sn_hr_workday_time_off_requests" version="3" view=""><sys_ui_element action="INSERT_OR_UPDATE"><element>.begin_split</element><position>0</position><sys_created_by>admin</sys_created_by><sys_created_on>2023-02-23 11:42:40</sys_created_on><sys_id>7b5d877b47456510901d3a34846d4352</sys_id><sys_mod_count>0</sys_mod_count><sys_ui_formatter/><sys_ui_section caption="NULL" display_value="" name="sn_hr_workday_time_off_requests" sys_domain="global" view="Default view">7b5d877b47456510901d3a34846d4326</sys_ui_section><sys_updated_by>admin</sys_updated_by><sys_updated_on>2023-02-23 11:42:40</sys_updated_on><sys_user/><type>.begin_split</type></sys_ui_element><sys_ui_element action="INSERT_OR_UPDATE"><element>u_type_of_leave</element><position>1</position><sys_created_by>admin</sys_created_by><sys_created_on>2023-02-23 11:42:40</sys_created_on><sys_id>fb5d877b47456510901d3a34846d4352</sys_id><sys_mod_count>0</sys_mod_count><sys_ui_formatter/><sys_ui_section caption="NULL" display_value="" name="sn_hr_workday_time_off_requests" sys_domain="global" view="Default view">7b5d877b47456510901d3a34846d4326</sys_ui_section><sys_updated_by>admin</sys_updated_by><sys_updated_on>2023-02-23 11:42:40</sys_updated_on><sys_user/><type/></sys_ui_element><sys_ui_element action="INSERT_OR_UPDATE"><element>u_total_requested_with_units</element><position>2</position><sys_created_by>admin</sys_created_by><sys_created_on>2023-02-23 11:42:40</sys_created_on><sys_id>7f5d877b47456510901d3a34846d4352</sys_id><sys_mod_count>0</sys_mod_count><sys_ui_formatter/><sys_ui_section caption="NULL" display_value="" name="sn_hr_workday_time_off_requests" sys_domain="global" view="Default view">7b5d877b47456510901d3a34846d4326</sys_ui_section><sys_updated_by>admin</sys_updated_by><sys_updated_on>2023-02-23 11:42:40</sys_updated_on><sys_user/><type/></sys_ui_element><sys_ui_element action="INSERT_OR_UPDATE"><element>u_first_day_of_time_off</element><position>3</position><sys_created_by>admin</sys_created_by><sys_created_on>2023-02-23 11:42:40</sys_created_on><sys_id>ff5d877b47456510901d3a34846d4352</sys_id><sys_mod_count>0</sys_mod_count><sys_ui_formatter/><sys_ui_section caption="NULL" display_value="" name="sn_hr_workday_time_off_requests" sys_domain="global" view="Default view">7b5d877b47456510901d3a34846d4326</sys_ui_section><sys_updated_by>admin</sys_updated_by><sys_updated_on>2023-02-23 11:42:40</sys_updated_on><sys_user/><type/></sys_ui_element><sys_ui_element action="INSERT_OR_UPDATE"><element>.split</element><position>4</position><sys_created_by>admin</sys_created_by><sys_created_on>2023-02-23 11:42:40</sys_created_on><sys_id>735d877b47456510901d3a34846d4353</sys_id><sys_mod_count>0</sys_mod_count><sys_ui_formatter/><sys_ui_section caption="NULL" display_value="" name="sn_hr_workday_time_off_requests" sys_domain="global" view="Default view">7b5d877b47456510901d3a34846d4326</sys_ui_section><sys_updated_by>admin</sys_updated_by><sys_updated_on>2023-02-23 11:42:40</sys_updated_on><sys_user/><type>.split</type></sys_ui_element><sys_ui_element action="INSERT_OR_UPDATE"><element>u_attachments</element><position>5</position><sys_created_by>admin</sys_created_by><sys_created_on>2023-02-23 11:42:40</sys_created_on><sys_id>f35d877b47456510901d3a34846d4353</sys_id><sys_mod_count>0</sys_mod_count><sys_ui_formatter/><sys_ui_section caption="NULL" display_value="" name="sn_hr_workday_time_off_requests" sys_domain="global" view="Default view">7b5d877b47456510901d3a34846d4326</sys_ui_section><sys_updated_by>admin</sys_updated_by><sys_updated_on>2023-02-23 11:42:40</sys_updated_on><sys_user/><type/></sys_ui_element><sys_ui_element action="INSERT_OR_UPDATE"><element>u_last_day_of_time_off</element><position>6</position><sys_created_by>admin</sys_created_by><sys_created_on>2023-02-23 11:42:40</sys_created_on><sys_id>775d877b47456510901d3a34846d4353</sys_id><sys_mod_count>0</sys_mod_count><sys_ui_formatter/><sys_ui_section caption="NULL" display_value="" name="sn_hr_workday_time_off_requests" sys_domain="global" view="Default view">7b5d877b47456510901d3a34846d4326</sys_ui_section><sys_updated_by>admin</sys_updated_by><sys_updated_on>2023-02-23 11:42:40</sys_updated_on><sys_user/><type/></sys_ui_element><sys_ui_element action="INSERT_OR_UPDATE"><element>u_comments</element><position>7</position><sys_created_by>admin</sys_created_by><sys_created_on>2023-02-23 11:42:40</sys_created_on><sys_id>f75d877b47456510901d3a34846d4353</sys_id><sys_mod_count>0</sys_mod_count><sys_ui_formatter/><sys_ui_section caption="NULL" display_value="" name="sn_hr_workday_time_off_requests" sys_domain="global" view="Default view">7b5d877b47456510901d3a34846d4326</sys_ui_section><sys_updated_by>admin</sys_updated_by><sys_updated_on>2023-02-23 11:42:40</sys_updated_on><sys_user/><type/></sys_ui_element><sys_ui_element action="INSERT_OR_UPDATE"><element>.end_split</element><position>8</position><sys_created_by>admin</sys_created_by><sys_created_on>2023-02-23 11:42:40</sys_created_on><sys_id>7b5d877b47456510901d3a34846d4353</sys_id><sys_mod_count>0</sys_mod_count><sys_ui_formatter/><sys_ui_section caption="NULL" display_value="" name="sn_hr_workday_time_off_requests" sys_domain="global" view="Default view">7b5d877b47456510901d3a34846d4326</sys_ui_section><sys_updated_by>admin</sys_updated_by><sys_updated_on>2023-02-23 11:42:40</sys_updated_on><sys_user/><type>.end_split</type></sys_ui_element><sys_ui_element action="INSERT_OR_UPDATE"><element>u_action_event</element><position>9</position><sys_created_by>admin</sys_created_by><sys_created_on>2023-02-24 08:49:26</sys_created_on><sys_id>c05f63848751a51018c742ec0ebb356d</sys_id><sys_mod_count>0</sys_mod_count><sys_ui_formatter/><sys_ui_section caption="NULL" display_value="" name="sn_hr_workday_time_off_requests" sys_domain="global" view="Default view">7b5d877b47456510901d3a34846d4326</sys_ui_section><sys_updated_by>admin</sys_updated_by><sys_updated_on>2023-02-24 08:49:26</sys_updated_on><sys_user/><type/></sys_ui_element><sys_ui_element action="INSERT_OR_UPDATE"><element>u_workday_todos</element><position>10</position><sys_created_by>admin</sys_created_by><sys_created_on>2023-02-24 11:29:19</sys_created_on><sys_id>b5e3581c4755a510901d3a34846d43f8</sys_id><sys_mod_count>0</sys_mod_count><sys_ui_formatter/><sys_ui_section caption="NULL" display_value="" name="sn_hr_workday_time_off_requests" sys_domain="global" view="Default view">7b5d877b47456510901d3a34846d4326</sys_ui_section><sys_updated_by>admin</sys_updated_by><sys_updated_on>2023-02-24 11:29:19</sys_updated_on><sys_user/><type/></sys_ui_element><sys_ui_element action="INSERT_OR_UPDATE"><element>u_workday_id</element><position>11</position><sys_created_by>admin</sys_created_by><sys_created_on>2023-02-27 05:13:25</sys_created_on><sys_id>30aa9e8d47dd2910901d3a34846d4353</sys_id><sys_mod_count>0</sys_mod_count><sys_ui_formatter/><sys_ui_section caption="NULL" display_value="" name="sn_hr_workday_time_off_requests" sys_domain="global" view="Default view">7b5d877b47456510901d3a34846d4326</sys_ui_section><sys_updated_by>admin</sys_updated_by><sys_updated_on>2023-02-27 05:13:25</sys_updated_on><sys_user/><type/></sys_ui_element><sys_ui_element action="INSERT_OR_UPDATE"><element>u_workdayid</element><position>12</position><sys_created_by>admin</sys_created_by><sys_created_on>2023-03-02 08:00:10</sys_created_on><sys_id>349d52c2475d2d10901d3a34846d43ca</sys_id><sys_mod_count>0</sys_mod_count><sys_ui_formatter/><sys_ui_section caption="NULL" display_value="" name="sn_hr_workday_time_off_requests" sys_domain="global" view="Default view">7b5d877b47456510901d3a34846d4326</sys_ui_section><sys_updated_by>admin</sys_updated_by><sys_updated_on>2023-03-02 08:00:10</sys_updated_on><sys_user/><type/></sys_ui_element><sys_ui_element action="INSERT_OR_UPDATE"><element>u_time_off_total_units_days</element><position>13</position><sys_created_by>admin</sys_created_by><sys_created_on>2023-03-02 08:00:26</sys_created_on><sys_id>38ad92c2475d2d10901d3a34846d438c</sys_id><sys_mod_count>0</sys_mod_count><sys_ui_formatter/><sys_ui_section caption="NULL" display_value="" name="sn_hr_workday_time_off_requests" sys_domain="global" view="Default view">7b5d877b47456510901d3a34846d4326</sys_ui_section><sys_updated_by>admin</sys_updated_by><sys_updated_on>2023-03-02 08:00:26</sys_updated_on><sys_user/><type/></sys_ui_element><sys_ui_element action="INSERT_OR_UPDATE"><element>u_time_off_total_units_hours</element><position>14</position><sys_created_by>admin</sys_created_by><sys_created_on>2023-03-02 08:00:34</sys_created_on><sys_id>32add2c2475d2d10901d3a34846d4319</sys_id><sys_mod_count>0</sys_mod_count><sys_ui_formatter/><sys_ui_section caption="NULL" display_value="" name="sn_hr_workday_time_off_requests" sys_domain="global" view="Default view">7b5d877b47456510901d3a34846d4326</sys_ui_section><sys_updated_by>admin</sys_updated_by><sys_updated_on>2023-03-02 08:00:34</sys_updated_on><sys_user/><type/></sys_ui_element><sys_ui_element action="INSERT_OR_UPDATE"><element>u_date</element><position>15</position><sys_created_by>admin</sys_created_by><sys_created_on>2023-03-02 08:00:40</sys_created_on><sys_id>08bdd2c2475d2d10901d3a34846d43a5</sys_id><sys_mod_count>0</sys_mod_count><sys_ui_formatter/><sys_ui_section caption="NULL" display_value="" name="sn_hr_workday_time_off_requests" sys_domain="global" view="Default view">7b5d877b47456510901d3a34846d4326</sys_ui_section><sys_updated_by>admin</sys_updated_by><sys_updated_on>2023-03-02 08:00:40</sys_updated_on><sys_user/><type/></sys_ui_element><sys_ui_element action="INSERT_OR_UPDATE"><element>u_day_of_the_week</element><position>16</position><sys_created_by>admin</sys_created_by><sys_created_on>2023-03-02 08:00:45</sys_created_on><sys_id>59bdd2c2475d2d10901d3a34846d43e7</sys_id><sys_mod_count>0</sys_mod_count><sys_ui_formatter/><sys_ui_section caption="NULL" display_value="" name="sn_hr_workday_time_off_requests" sys_domain="global" view="Default view">7b5d877b47456510901d3a34846d4326</sys_ui_section><sys_updated_by>admin</sys_updated_by><sys_updated_on>2023-03-02 08:00:45</sys_updated_on><sys_user/><type/></sys_ui_element><sys_ui_element action="INSERT_OR_UPDATE"><element>u_time_off_type_for_time_off_entry</element><position>17</position><sys_created_by>admin</sys_created_by><sys_created_on>2023-03-02 08:00:50</sys_created_on><sys_id>6abd16c2475d2d10901d3a34846d4342</sys_id><sys_mod_count>0</sys_mod_count><sys_ui_formatter/><sys_ui_section caption="NULL" display_value="" name="sn_hr_workday_time_off_requests" sys_domain="global" view="Default view">7b5d877b47456510901d3a34846d4326</sys_ui_section><sys_updated_by>admin</sys_updated_by><sys_updated_on>2023-03-02 08:00:50</sys_updated_on><sys_user/><type/></sys_ui_element><sys_ui_element action="INSERT_OR_UPDATE"><element>u_units_requested_this_coordinated_leave_time_off</element><position>18</position><sys_created_by>admin</sys_created_by><sys_created_on>2023-03-02 08:00:54</sys_created_on><sys_id>afbd16c2475d2d10901d3a34846d436b</sys_id><sys_mod_count>0</sys_mod_count><sys_ui_formatter/><sys_ui_section caption="NULL" display_value="" name="sn_hr_workday_time_off_requests" sys_domain="global" view="Default view">7b5d877b47456510901d3a34846d4326</sys_ui_section><sys_updated_by>admin</sys_updated_by><sys_updated_on>2023-03-02 08:00:54</sys_updated_on><sys_user/><type/></sys_ui_element><sys_ui_element action="INSERT_OR_UPDATE"><element>u_unitoftime</element><position>19</position><sys_created_by>admin</sys_created_by><sys_created_on>2023-03-02 08:00:57</sys_created_on><sys_id>d8cd16c2475d2d10901d3a34846d43a1</sys_id><sys_mod_count>0</sys_mod_count><sys_ui_formatter/><sys_ui_section caption="NULL" display_value="" name="sn_hr_workday_time_off_requests" sys_domain="global" view="Default view">7b5d877b47456510901d3a34846d4326</sys_ui_section><sys_updated_by>admin</sys_updated_by><sys_updated_on>2023-03-02 08:00:57</sys_updated_on><sys_user/><type/></sys_ui_element><sys_ui_element action="INSERT_OR_UPDATE"><element>u_taskitemuniqueid</element><position>20</position><sys_created_by>admin</sys_created_by><sys_created_on>2023-03-02 08:40:05</sys_created_on><sys_id>29b6a6ca475d2d10901d3a34846d43c5</sys_id><sys_mod_count>0</sys_mod_count><sys_ui_formatter/><sys_ui_section caption="NULL" display_value="" name="sn_hr_workday_time_off_requests" sys_domain="global" view="Default view">7b5d877b47456510901d3a34846d4326</sys_ui_section><sys_updated_by>admin</sys_updated_by><sys_updated_on>2023-03-02 08:40:05</sys_updated_on><sys_user/><type/></sys_ui_element><sys_ui_element action="INSERT_OR_UPDATE"><element>u_time_off_request_parent</element><position>21</position><sys_created_by>admin</sys_created_by><sys_created_on>2023-03-23 05:57:59</sys_created_on><sys_id>bffa02b047312150901d3a34846d4303</sys_id><sys_mod_count>0</sys_mod_count><sys_ui_formatter/><sys_ui_section caption="NULL" display_value="" name="sn_hr_workday_time_off_requests" sys_domain="global" view="Default view">7b5d877b47456510901d3a34846d4326</sys_ui_section><sys_updated_by>admin</sys_updated_by><sys_updated_on>2023-03-23 05:57:59</sys_updated_on><sys_user/><type/></sys_ui_element><sys_ui_element action="INSERT_OR_UPDATE"><element>u_use_case_type</element><position>22</position><sys_created_by>admin</sys_created_by><sys_created_on>2023-03-31 05:37:12</sys_created_on><sys_id>91f2df5787fd611018c742ec0ebb358f</sys_id><sys_mod_count>0</sys_mod_count><sys_ui_formatter/><sys_ui_section caption="NULL" display_value="" name="sn_hr_workday_time_off_requests" sys_domain="global" view="Default view">7b5d877b47456510901d3a34846d4326</sys_ui_section><sys_updated_by>admin</sys_updated_by><sys_updated_on>2023-03-31 05:37:12</sys_updated_on><sys_user/><type/></sys_ui_element><sys_ui_section action="INSERT_OR_UPDATE"><caption/><header>false</header><name>sn_hr_workday_time_off_requests</name><roles/><sys_class_name>sys_ui_section</sys_class_name><sys_created_by>admin</sys_created_by><sys_created_on>2023-02-23 11:42:40</sys_created_on><sys_domain>global</sys_domain><sys_domain_path>/</sys_domain_path><sys_id>7b5d877b47456510901d3a34846d4326</sys_id><sys_mod_count>0</sys_mod_count><sys_name>sn_hr_workday_time_off_requests</sys_name><sys_overrides/><sys_package display_value="HR Service Delivery Integration with Workday" source="sn_hr_workday">d4fb8bd8db5b0010205cdf6b5e96190e</sys_package><sys_policy/><sys_scope display_value="HR Service Delivery Integration with Workday">d4fb8bd8db5b0010205cdf6b5e96190e</sys_scope><sys_update_name>sys_ui_section_7b5d877b47456510901d3a34846d4326</sys_update_name><sys_updated_by>admin</sys_updated_by><sys_updated_on>2023-02-23 11:42:40</sys_updated_on><sys_user/><title>true</title><view display_value="Default view" name="NULL">Default view</view><view_name/></sys_ui_section></sys_ui_section></record_update>]]></payload>
        <payload_hash>1797098906</payload_hash>
        <record_name>Time off requests</record_name>
        <reverted_from/>
        <source>80bae28c4772611072cf2ebd416d435c</source>
        <source_table>sys_update_set</source_table>
        <state>previous</state>
        <sys_created_by>admin</sys_created_by>
        <sys_created_on>2023-05-09 17:26:31</sys_created_on>
        <sys_id>c85b264047b2611072cf2ebd416d43f8</sys_id>
        <sys_mod_count>0</sys_mod_count>
        <sys_recorded_at>188018ce7bc0000001</sys_recorded_at>
        <sys_updated_by>admin</sys_updated_by>
        <sys_updated_on>2023-05-09 17:26:31</sys_updated_on>
        <type>Form Layout</type>
        <update_guid>99f25397b6fd6110154f758673cb322c</update_guid>
        <update_guid_history>99f25397b6fd6110154f758673cb322c:1797098906,b7fac2b0cd31215061c4d58e1a0623dd:-1888456078,29b6a6caab5d2d100c63e06794e6cdc8:1275187012,50cd16c2715d2d10276f44370687e0a4:-1511661193,e3bd16c2ee5d2d1028bdc0ca5d9b866e:473084252,6ebd16c2b25d2d1070b4f06e80178944:234181118,2dbdd2c2b65d2d10337812cd8bf689e9:-1503996412,98bdd2c27c5d2d10d3eb90163094ada7:-65597469,72add2c2655d2d10c2299a2b2bb5251b:1626592838,09ad92c21c5d2d101d1bcd155dfb4f8e:-714659754,bc9d52c2615d2d10e77996b5d71d0ccc:-835999413,f4aa9e8df5dd2910ed204cccbb29f355:203523863,cee3945cc455a510dfaf232300847751:-1108906179,c45f63840351a51044834d972816696f:-100030442,735d877bae45651080055dee3b59b855:-1919749295,b35d877b1845651005c24e89e1f5fe29:1264764030</update_guid_history>
    </sys_update_version>
    <sys_metadata_delete action="INSERT_OR_UPDATE">
        <sys_audit_delete/>
        <sys_class_name>sys_metadata_delete</sys_class_name>
        <sys_created_by>admin</sys_created_by>
        <sys_created_on>2023-05-09 18:04:06</sys_created_on>
        <sys_db_object display_value="" name="sys_ui_section">sys_ui_section</sys_db_object>
        <sys_id>61a0570ed53a4e25a6f7a4ee4e697381</sys_id>
        <sys_metadata>7b5d877b47456510901d3a34846d4326</sys_metadata>
        <sys_mod_count>0</sys_mod_count>
        <sys_name>sn_hr_workday_time_off_requests</sys_name>
        <sys_package display_value="HR Service Delivery Integration with Workday" source="sn_hr_workday">d4fb8bd8db5b0010205cdf6b5e96190e</sys_package>
        <sys_parent/>
        <sys_policy/>
        <sys_scope display_value="HR Service Delivery Integration with Workday">d4fb8bd8db5b0010205cdf6b5e96190e</sys_scope>
        <sys_scope_delete display_value="">2b72f0f872474230a9dbcdf31f5e5440</sys_scope_delete>
        <sys_update_name>sys_ui_section_7b5d877b47456510901d3a34846d4326</sys_update_name>
        <sys_update_version display_value="sys_ui_section_7b5d877b47456510901d3a34846d4326">c85b264047b2611072cf2ebd416d43f8</sys_update_version>
        <sys_updated_by>admin</sys_updated_by>
        <sys_updated_on>2023-05-09 18:04:06</sys_updated_on>
    </sys_metadata_delete>
</record_update>
